easy_filters/__init__.py
easy_filters/filters.py
easy_filters/webcam.py
easy_filters-0.1.1.dist-info/METADATA
easy_filters-0.1.1.dist-info/WHEEL
easy_filters-0.1.1.dist-info/top_level.txt
easy_filters-0.1.1.dist-info/RECORD
