Metadata-Version: 2.4
Name: easy-filters
Version: 0.1.1
Summary: A simple Python library for real-time webcam filters
Author: Anisha Mhatre
Author-email: anisha.mhatre3@gmail.com
Classifier: Programming Language :: Python :: 3
Classifier: License :: OSI Approved :: MIT License
Classifier: Operating System :: OS Independent
Requires-Python: >=3.6
Requires-Dist: numpy
Requires-Dist: opencv-contrib-python
Dynamic: author
Dynamic: author-email
Dynamic: classifier
Dynamic: description
Dynamic: description-content-type
Dynamic: requires-dist
Dynamic: requires-python
Dynamic: summary
